[
  {
    "time": "Sep 21 07:01:43.505",
    "process": "bt_player",
    "pid": "353",
    "message": "19:36:07, e[32mINFO e[0m e[90mprint_monitor:223:e[0m  TTS   <X:X> [63894034903] play[KIT_IDLE] vol[60]"
  },
  {
    "time": "Sep 21 07:00:50.536",
    "process": "bt_player",
    "pid": "451",
    "message": "19:56:29, e[32mINFO e[0m e[90mprint_monitor:223:e[0m  TTS   <X:X> [63894034850] play[KIT_IDLE] vol[60]"
  },
  {
    "time": "Sep 21 06:56:10.389",
    "process": "bt_player",
    "pid": "847",
    "message": "13:20:40, e[32mINFO e[0m e[90mprint_monitor:191:e[0m  BT    <X:X> [63894034570] power[1] discov[0] conn[0[] play[0] trans[BT_TRANSPORT_DISCONNECT:BT_TRANSPORT_IDLE] vol[64])"
  },
  {
    "time": "Sep 21 06:55:35.339",
    "process": "bt_player",
    "pid": "710",
    "message": "02:37:27, e[32mINFO e[0m e[90mprint_monitor:191:e[0m  BT    <X:X> [63894034535] power[1] discov[0] conn[0[] play[0] trans[BT_TRANSPORT_DISCONNECT:BT_TRANSPORT_IDLE] vol[64])"
  },
  {
    "time": "Sep 21 06:53:14.306",
    "process": "bt_player",
    "pid": "328",
    "message": "08:13:23, e[32mINFO e[0m e[90mprint_monitor:223:e[0m  TTS   <X:X> [63894034394] play[KIT_IDLE] vol[60]"
  },
  {
    "time": "Sep 21 06:49:13.543",
    "process": "bt_player",
    "pid": "516",
    "message": "06:29:32, e[32mINFO e[0m e[90mprint_monitor:223:e[0m  TTS   <X:X> [63894034153] play[KIT_IDLE] vol[60]"
  },
  {
    "time": "Sep 21 06:46:12.281",
    "process": "bt_player",
    "pid": "891",
    "message": "23:02:13, e[32mINFO e[0m e[90mprint_monitor:205:e[0m  MEDIA <X:X> [63894033972] play[KIT_STOPPED:000/000000] LED[0] HS[0] hplay[2] H_ID(000:-01) MT[1] vol[50]"
  },
  {
    "time": "Sep 21 06:44:26.948",
    "process": "bt_player",
    "pid": "154",
    "message": "14:45:30, e[32mINFO e[0m e[90mprint_monitor:191:e[0m  BT    <X:X> [63894033866] power[1] discov[0] conn[0[] play[0] trans[BT_TRANSPORT_DISCONNECT:BT_TRANSPORT_IDLE] vol[64])"
  },
  {
    "time": "Sep 21 06:32:48.755",
    "process": "bt_player",
    "pid": "563",
    "message": "13:08:19, e[32mINFO e[0m e[90mprint_monitor:205:e[0m  MEDIA <X:X> [63894033168] play[KIT_STOPPED:000/000000] LED[0] HS[0] hplay[2] H_ID(000:-01) MT[1] vol[50]"
  },
  {
    "time": "Sep 21 06:32:04.549",
    "process": "bt_player",
    "pid": "394",
    "message": "14:40:55, e[32mINFO e[0m e[90mprint_monitor:223:e[0m  TTS   <X:X> [63894033124] play[KIT_IDLE] vol[60]"
  },
  {
    "time": "Sep 21 06:30:51.160",
    "process": "bt_player",
    "pid": "271",
    "message": "13:55:21, e[32mINFO e[0m e[90mprint_monitor:223:e[0m  TTS   <X:X> [63894033051] play[KIT_IDLE] vol[60]"
  },
  {
    "time": "Sep 21 06:28:32.774",
    "process": "bt_player",
    "pid": "766",
    "message": "16:03:08, e[32mINFO e[0m e[90mprint_monitor:205:e[0m  MEDIA <X:X> [63894032912] play[KIT_STOPPED:000/000000] LED[0] HS[0] hplay[2] H_ID(000:-01) MT[1] vol[50]"
  },
  {
    "time": "Sep 21 06:24:01.629",
    "process": "bt_player",
    "pid": "522",
    "message": "20:11:38, e[32mINFO e[0m e[90mprint_monitor:191:e[0m  BT    <X:X> [63894032641] power[1] discov[0] conn[0[] play[0] trans[BT_TRANSPORT_DISCONNECT:BT_TRANSPORT_IDLE] vol[64])"
  },
  {
    "time": "Sep 21 06:19:49.304",
    "process": "bt_player",
    "pid": "940",
    "message": "02:28:55, e[32mINFO e[0m e[90mprint_monitor:223:e[0m  TTS   <X:X> [63894032389] play[KIT_IDLE] vol[60]"
  },
  {
    "time": "Sep 21 06:18:40.714",
    "process": "bt_player",
    "pid": "708",
    "message": "11:46:14, e[32mINFO e[0m e[90mprint_monitor:191:e[0m  BT    <X:X> [63894032320] power[1] discov[0] conn[0[] play[0] trans[BT_TRANSPORT_DISCONNECT:BT_TRANSPORT_IDLE] vol[64])"
  },
  {
    "time": "Sep 21 06:17:44.656",
    "process": "bt_player",
    "pid": "107",
    "message": "09:07:57, e[32mINFO e[0m e[90mprint_monitor:191:e[0m  BT    <X:X> [63894032264] power[1] discov[0] conn[0[] play[0] trans[BT_TRANSPORT_DISCONNECT:BT_TRANSPORT_IDLE] vol[64])"
  },
  {
    "time": "Sep 21 06:15:49.146",
    "process": "bt_player",
    "pid": "661",
    "message": "21:27:09, e[32mINFO e[0m e[90mprint_monitor:205:e[0m  MEDIA <X:X> [63894032149] play[KIT_STOPPED:000/000000] LED[0] HS[0] hplay[2] H_ID(000:-01) MT[1] vol[50]"
  },
  {
    "time": "Sep 21 06:15:36.335",
    "process": "bt_player",
    "pid": "116",
    "message": "21:05:23, e[32mINFO e[0m e[90mprint_monitor:191:e[0m  BT    <X:X> [63894032136] power[1] discov[0] conn[0[] play[0] trans[BT_TRANSPORT_DISCONNECT:BT_TRANSPORT_IDLE] vol[64])"
  },
  {
    "time": "Sep 21 06:13:12.638",
    "process": "bt_player",
    "pid": "715",
    "message": "09:31:11, e[32mINFO e[0m e[90mprint_monitor:191:e[0m  BT    <X:X> [63894031992] power[1] discov[0] conn[0[] play[0] trans[BT_TRANSPORT_DISCONNECT:BT_TRANSPORT_IDLE] vol[64])"
  },
  {
    "time": "Sep 21 06:12:14.299",
    "process": "bt_player",
    "pid": "113",
    "message": "21:19:01, e[32mINFO e[0m e[90mprint_monitor:205:e[0m  MEDIA <X:X> [63894031934] play[KIT_STOPPED:000/000000] LED[0] HS[0] hplay[2] H_ID(000:-01) MT[1] vol[50]"
  },
  {
    "time": "Sep 21 06:11:43.398",
    "process": "bt_player",
    "pid": "304",
    "message": "13:47:00, e[32mINFO e[0m e[90mprint_monitor:205:e[0m  MEDIA <X:X> [63894031903] play[KIT_STOPPED:000/000000] LED[0] HS[0] hplay[2] H_ID(000:-01) MT[1] vol[50]"
  },
  {
    "time": "Sep 21 06:11:16.600",
    "process": "bt_player",
    "pid": "980",
    "message": "00:23:09, e[32mINFO e[0m e[90mprint_monitor:223:e[0m  TTS   <X:X> [63894031876] play[KIT_IDLE] vol[60]"
  },
  {
    "time": "Sep 21 06:09:27.389",
    "process": "bt_player",
    "pid": "736",
    "message": "10:08:48, e[32mINFO e[0m e[90mprint_monitor:191:e[0m  BT    <X:X> [63894031767] power[1] discov[0] conn[0[] play[0] trans[BT_TRANSPORT_DISCONNECT:BT_TRANSPORT_IDLE] vol[64])"
  },
  {
    "time": "Sep 21 06:07:26.949",
    "process": "bt_player",
    "pid": "945",
    "message": "09:23:21, e[32mINFO e[0m e[90mprint_monitor:223:e[0m  TTS   <X:X> [63894031646] play[KIT_IDLE] vol[60]"
  },
  {
    "time": "Sep 21 06:05:10.833",
    "process": "bt_player",
    "pid": "372",
    "message": "20:29:38, e[32mINFO e[0m e[90mprint_monitor:223:e[0m  TTS   <X:X> [63894031510] play[KIT_IDLE] vol[60]"
  },
  {
    "time": "Sep 21 05:51:14.983",
    "process": "bt_player",
    "pid": "642",
    "message": "04:27:07, e[32mINFO e[0m e[90mprint_monitor:223:e[0m  TTS   <X:X> [63894030674] play[KIT_IDLE] vol[60]"
  },
  {
    "time": "Sep 21 05:50:21.796",
    "process": "bt_player",
    "pid": "501",
    "message": "02:59:48, e[32mINFO e[0m e[90mprint_monitor:205:e[0m  MEDIA <X:X> [63894030621] play[KIT_STOPPED:000/000000] LED[0] HS[0] hplay[2] H_ID(000:-01) MT[1] vol[50]"
  },
  {
    "time": "Sep 21 05:46:51.044",
    "process": "bt_player",
    "pid": "593",
    "message": "11:49:37, e[32mINFO e[0m e[90mprint_monitor:223:e[0m  TTS   <X:X> [63894030411] play[KIT_IDLE] vol[60]"
  },
  {
    "time": "Sep 21 05:43:47.850",
    "process": "bt_player",
    "pid": "802",
    "message": "20:16:31, e[32mINFO e[0m e[90mprint_monitor:223:e[0m  TTS   <X:X> [63894030227] play[KIT_IDLE] vol[60]"
  },
  {
    "time": "Sep 21 05:43:22.539",
    "process": "bt_player",
    "pid": "606",
    "message": "04:30:49, e[32mINFO e[0m e[90mprint_monitor:205:e[0m  MEDIA <X:X> [63894030202] play[KIT_STOPPED:000/000000] LED[0] HS[0] hplay[2] H_ID(000:-01) MT[1] vol[50]"
  },
  {
    "time": "Sep 21 05:43:09.354",
    "process": "bt_player",
    "pid": "279",
    "message": "10:26:34, e[32mINFO e[0m e[90mprint_monitor:205:e[0m  MEDIA <X:X> [63894030189] play[KIT_STOPPED:000/000000] LED[0] HS[0] hplay[2] H_ID(000:-01) MT[1] vol[50]"
  },
  {
    "time": "Sep 21 05:42:41.948",
    "process": "bt_player",
    "pid": "780",
    "message": "05:28:14, e[32mINFO e[0m e[90mprint_monitor:205:e[0m  MEDIA <X:X> [63894030161] play[KIT_STOPPED:000/000000] LED[0] HS[0] hplay[2] H_ID(000:-01) MT[1] vol[50]"
  },
  {
    "time": "Sep 21 05:31:28.600",
    "process": "bt_player",
    "pid": "754",
    "message": "16:44:11, e[32mINFO e[0m e[90mprint_monitor:191:e[0m  BT    <X:X> [63894029488] power[1] discov[0] conn[0[] play[0] trans[BT_TRANSPORT_DISCONNECT:BT_TRANSPORT_IDLE] vol[64])"
  },
  {
    "time": "Sep 21 05:30:30.683",
    "process": "bt_player",
    "pid": "406",
    "message": "05:55:48, e[32mINFO e[0m e[90mprint_monitor:191:e[0m  BT    <X:X> [63894029430] power[1] discov[0] conn[0[] play[0] trans[BT_TRANSPORT_DISCONNECT:BT_TRANSPORT_IDLE] vol[64])"
  },
  {
    "time": "Sep 21 05:27:24.247",
    "process": "bt_player",
    "pid": "441",
    "message": "11:16:41, e[32mINFO e[0m e[90mprint_monitor:191:e[0m  BT    <X:X> [63894029244] power[1] discov[0] conn[0[] play[0] trans[BT_TRANSPORT_DISCONNECT:BT_TRANSPORT_IDLE] vol[64])"
  },
  {
    "time": "Sep 21 05:26:01.389",
    "process": "bt_player",
    "pid": "475",
    "message": "04:41:05, e[32mINFO e[0m e[90mprint_monitor:223:e[0m  TTS   <X:X> [63894029161] play[KIT_IDLE] vol[60]"
  },
  {
    "time": "Sep 21 05:25:15.715",
    "process": "bt_player",
    "pid": "173",
    "message": "02:34:17, e[32mINFO e[0m e[90mprint_monitor:223:e[0m  TTS   <X:X> [63894029115] play[KIT_IDLE] vol[60]"
  },
  {
    "time": "Sep 21 05:24:12.915",
    "process": "bt_player",
    "pid": "141",
    "message": "12:46:12, e[32mINFO e[0m e[90mprint_monitor:223:e[0m  TTS   <X:X> [63894029052] play[KIT_IDLE] vol[60]"
  },
  {
    "time": "Sep 21 05:23:53.124",
    "process": "bt_player",
    "pid": "502",
    "message": "05:25:13, e[32mINFO e[0m e[90mprint_monitor:191:e[0m  BT    <X:X> [63894029033] power[1] discov[0] conn[0[] play[0] trans[BT_TRANSPORT_DISCONNECT:BT_TRANSPORT_IDLE] vol[64])"
  },
  {
    "time": "Sep 21 05:21:40.557",
    "process": "bt_player",
    "pid": "904",
    "message": "21:11:10, e[32mINFO e[0m e[90mprint_monitor:191:e[0m  BT    <X:X> [63894028900] power[1] discov[0] conn[0[] play[0] trans[BT_TRANSPORT_DISCONNECT:BT_TRANSPORT_IDLE] vol[64])"
  },
  {
    "time": "Sep 21 05:18:06.177",
    "process": "bt_player",
    "pid": "208",
    "message": "17:09:24, e[32mINFO e[0m e[90mprint_monitor:223:e[0m  TTS   <X:X> [63894028686] play[KIT_IDLE] vol[60]"
  },
  {
    "time": "Sep 21 05:17:23.986",
    "process": "bt_player",
    "pid": "785",
    "message": "07:28:01, e[32mINFO e[0m e[90mprint_monitor:205:e[0m  MEDIA <X:X> [63894028643] play[KIT_STOPPED:000/000000] LED[0] HS[0] hplay[2] H_ID(000:-01) MT[1] vol[50]"
  },
  {
    "time": "Sep 21 05:14:54.088",
    "process": "bt_player",
    "pid": "679",
    "message": "21:05:46, e[32mINFO e[0m e[90mprint_monitor:205:e[0m  MEDIA <X:X> [63894028494] play[KIT_STOPPED:000/000000] LED[0] HS[0] hplay[2] H_ID(000:-01) MT[1] vol[50]"
  },
  {
    "time": "Sep 21 05:14:19.445",
    "process": "bt_player",
    "pid": "449",
    "message": "08:20:44, e[32mINFO e[0m e[90mprint_monitor:223:e[0m  TTS   <X:X> [63894028459] play[KIT_IDLE] vol[60]"
  },
  {
    "time": "Sep 21 05:13:34.057",
    "process": "bt_player",
    "pid": "369",
    "message": "04:47:26, e[32mINFO e[0m e[90mprint_monitor:191:e[0m  BT    <X:X> [63894028414] power[1] discov[0] conn[0[] play[0] trans[BT_TRANSPORT_DISCONNECT:BT_TRANSPORT_IDLE] vol[64])"
  },
  {
    "time": "Sep 21 05:07:18.617",
    "process": "bt_player",
    "pid": "675",
    "message": "04:10:07, e[32mINFO e[0m e[90mprint_monitor:223:e[0m  TTS   <X:X> [63894028038] play[KIT_IDLE] vol[60]"
  },
  {
    "time": "Sep 21 05:05:07.258",
    "process": "bt_player",
    "pid": "189",
    "message": "06:57:57, e[32mINFO e[0m e[90mprint_monitor:205:e[0m  MEDIA <X:X> [63894027907] play[KIT_STOPPED:000/000000] LED[0] HS[0] hplay[2] H_ID(000:-01) MT[1] vol[50]"
  },
  {
    "time": "Sep 21 05:01:30.274",
    "process": "bt_player",
    "pid": "470",
    "message": "04:51:23, e[32mINFO e[0m e[90mprint_monitor:205:e[0m  MEDIA <X:X> [63894027690] play[KIT_STOPPED:000/000000] LED[0] HS[0] hplay[2] H_ID(000:-01) MT[1] vol[50]"
  },
  {
    "time": "Sep 21 05:00:22.456",
    "process": "bt_player",
    "pid": "172",
    "message": "06:12:05, e[32mINFO e[0m e[90mprint_monitor:191:e[0m  BT    <X:X> [63894027622] power[1] discov[0] conn[0[] play[0] trans[BT_TRANSPORT_DISCONNECT:BT_TRANSPORT_IDLE] vol[64])"
  },
  {
    "time": "Sep 21 04:59:26.147",
    "process": "bt_player",
    "pid": "474",
    "message": "18:02:05, e[32mINFO e[0m e[90mprint_monitor:205:e[0m  MEDIA <X:X> [63894027566] play[KIT_STOPPED:000/000000] LED[0] HS[0] hplay[2] H_ID(000:-01) MT[1] vol[50]"
  },
  {
    "time": "Sep 21 04:58:27.219",
    "process": "bt_player",
    "pid": "146",
    "message": "01:38:51, e[32mINFO e[0m e[90mprint_monitor:223:e[0m  TTS   <X:X> [63894027507] play[KIT_IDLE] vol[60]"
  },
  {
    "time": "Sep 21 04:57:55.393",
    "process": "bt_player",
    "pid": "374",
    "message": "06:07:15, e[32mINFO e[0m e[90mprint_monitor:223:e[0m  TTS   <X:X> [63894027475] play[KIT_IDLE] vol[60]"
  },
  {
    "time": "Sep 21 04:53:01.539",
    "process": "bt_player",
    "pid": "689",
    "message": "06:14:55, e[32mINFO e[0m e[90mprint_monitor:191:e[0m  BT    <X:X> [63894027181] power[1] discov[0] conn[0[] play[0] trans[BT_TRANSPORT_DISCONNECT:BT_TRANSPORT_IDLE] vol[64])"
  },
  {
    "time": "Sep 21 04:51:08.433",
    "process": "bt_player",
    "pid": "789",
    "message": "01:37:16, e[32mINFO e[0m e[90mprint_monitor:191:e[0m  BT    <X:X> [63894027068] power[1] discov[0] conn[0[] play[0] trans[BT_TRANSPORT_DISCONNECT:BT_TRANSPORT_IDLE] vol[64])"
  },
  {
    "time": "Sep 21 04:50:35.438",
    "process": "bt_player",
    "pid": "191",
    "message": "09:43:39, e[32mINFO e[0m e[90mprint_monitor:223:e[0m  TTS   <X:X> [63894027035] play[KIT_IDLE] vol[60]"
  },
  {
    "time": "Sep 21 04:49:26.410",
    "process": "bt_player",
    "pid": "379",
    "message": "05:43:42, e[32mINFO e[0m e[90mprint_monitor:205:e[0m  MEDIA <X:X> [63894026966] play[KIT_STOPPED:000/000000] LED[0] HS[0] hplay[2] H_ID(000:-01) MT[1] vol[50]"
  },
  {
    "time": "Sep 21 04:45:29.154",
    "process": "bt_player",
    "pid": "252",
    "message": "09:23:32, e[32mINFO e[0m e[90mprint_monitor:191:e[0m  BT    <X:X> [63894026729] power[1] discov[0] conn[0[] play[0] trans[BT_TRANSPORT_DISCONNECT:BT_TRANSPORT_IDLE] vol[64])"
  },
  {
    "time": "Sep 21 04:42:31.687",
    "process": "bt_player",
    "pid": "833",
    "message": "05:23:08, e[32mINFO e[0m e[90mprint_monitor:205:e[0m  MEDIA <X:X> [63894026551] play[KIT_STOPPED:000/000000] LED[0] HS[0] hplay[2] H_ID(000:-01) MT[1] vol[50]"
  },
  {
    "time": "Sep 21 04:40:55.014",
    "process": "bt_player",
    "pid": "244",
    "message": "17:53:50, e[32mINFO e[0m e[90mprint_monitor:191:e[0m  BT    <X:X> [63894026455] power[1] discov[0] conn[0[] play[0] trans[BT_TRANSPORT_DISCONNECT:BT_TRANSPORT_IDLE] vol[64])"
  },
  {
    "time": "Sep 21 04:36:38.755",
    "process": "bt_player",
    "pid": "983",
    "message": "22:42:01, e[32mINFO e[0m e[90mprint_monitor:191:e[0m  BT    <X:X> [63894026198] power[1] discov[0] conn[0[] play[0] trans[BT_TRANSPORT_DISCONNECT:BT_TRANSPORT_IDLE] vol[64])"
  },
  {
    "time": "Sep 21 04:35:46.443",
    "process": "bt_player",
    "pid": "390",
    "message": "23:06:49, e[32mINFO e[0m e[90mprint_monitor:191:e[0m  BT    <X:X> [63894026146] power[1] discov[0] conn[0[] play[0] trans[BT_TRANSPORT_DISCONNECT:BT_TRANSPORT_IDLE] vol[64])"
  },
  {
    "time": "Sep 21 04:35:16.500",
    "process": "bt_player",
    "pid": "520",
    "message": "04:52:02, e[32mINFO e[0m e[90mprint_monitor:191:e[0m  BT    <X:X> [63894026116] power[1] discov[0] conn[0[] play[0] trans[BT_TRANSPORT_DISCONNECT:BT_TRANSPORT_IDLE] vol[64])"
  },
  {
    "time": "Sep 21 04:34:45.197",
    "process": "bt_player",
    "pid": "975",
    "message": "10:23:57, e[32mINFO e[0m e[90mprint_monitor:205:e[0m  MEDIA <X:X> [63894026085] play[KIT_STOPPED:000/000000] LED[0] HS[0] hplay[2] H_ID(000:-01) MT[1] vol[50]"
  },
  {
    "time": "Sep 21 04:34:39.556",
    "process": "bt_player",
    "pid": "699",
    "message": "19:33:09, e[32mINFO e[0m e[90mprint_monitor:191:e[0m  BT    <X:X> [63894026079] power[1] discov[0] conn[0[] play[0] trans[BT_TRANSPORT_DISCONNECT:BT_TRANSPORT_IDLE] vol[64])"
  },
  {
    "time": "Sep 21 04:32:39.219",
    "process": "bt_player",
    "pid": "816",
    "message": "02:05:55, e[32mINFO e[0m e[90mprint_monitor:223:e[0m  TTS   <X:X> [63894025959] play[KIT_IDLE] vol[60]"
  },
  {
    "time": "Sep 21 04:32:38.432",
    "process": "bt_player",
    "pid": "733",
    "message": "03:07:19, e[32mINFO e[0m e[90mprint_monitor:205:e[0m  MEDIA <X:X> [63894025958] play[KIT_STOPPED:000/000000] LED[0] HS[0] hplay[2] H_ID(000:-01) MT[1] vol[50]"
  },
  {
    "time": "Sep 21 04:31:05.207",
    "process": "bt_player",
    "pid": "415",
    "message": "18:49:24, e[32mINFO e[0m e[90mprint_monitor:191:e[0m  BT    <X:X> [63894025865] power[1] discov[0] conn[0[] play[0] trans[BT_TRANSPORT_DISCONNECT:BT_TRANSPORT_IDLE] vol[64])"
  },
  {
    "time": "Sep 21 04:30:19.674",
    "process": "bt_player",
    "pid": "594",
    "message": "23:44:25, e[32mINFO e[0m e[90mprint_monitor:223:e[0m  TTS   <X:X> [63894025819] play[KIT_IDLE] vol[60]"
  },
  {
    "time": "Sep 21 04:22:53.430",
    "process": "bt_player",
    "pid": "310",
    "message": "07:33:44, e[32mINFO e[0m e[90mprint_monitor:223:e[0m  TTS   <X:X> [63894025373] play[KIT_IDLE] vol[60]"
  },
  {
    "time": "Sep 21 04:19:51.202",
    "process": "bt_player",
    "pid": "383",
    "message": "03:28:12, e[32mINFO e[0m e[90mprint_monitor:191:e[0m  BT    <X:X> [63894025191] power[1] discov[0] conn[0[] play[0] trans[BT_TRANSPORT_DISCONNECT:BT_TRANSPORT_IDLE] vol[64])"
  },
  {
    "time": "Sep 21 04:19:15.866",
    "process": "bt_player",
    "pid": "497",
    "message": "23:10:20, e[32mINFO e[0m e[90mprint_monitor:223:e[0m  TTS   <X:X> [63894025155] play[KIT_IDLE] vol[60]"
  },
  {
    "time": "Sep 21 04:15:08.804",
    "process": "bt_player",
    "pid": "727",
    "message": "06:19:34, e[32mINFO e[0m e[90mprint_monitor:205:e[0m  MEDIA <X:X> [63894024908] play[KIT_STOPPED:000/000000] LED[0] HS[0] hplay[2] H_ID(000:-01) MT[1] vol[50]"
  },
  {
    "time": "Sep 21 04:10:36.002",
    "process": "bt_player",
    "pid": "625",
    "message": "17:17:20, e[32mINFO e[0m e[90mprint_monitor:223:e[0m  TTS   <X:X> [63894024636] play[KIT_IDLE] vol[60]"
  },
  {
    "time": "Sep 21 04:07:05.769",
    "process": "bt_player",
    "pid": "356",
    "message": "05:05:21, e[32mINFO e[0m e[90mprint_monitor:191:e[0m  BT    <X:X> [63894024425] power[1] discov[0] conn[0[] play[0] trans[BT_TRANSPORT_DISCONNECT:BT_TRANSPORT_IDLE] vol[64])"
  },
  {
    "time": "Sep 21 04:06:02.427",
    "process": "bt_player",
    "pid": "596",
    "message": "13:17:39, e[32mINFO e[0m e[90mprint_monitor:205:e[0m  MEDIA <X:X> [63894024362] play[KIT_STOPPED:000/000000] LED[0] HS[0] hplay[2] H_ID(000:-01) MT[1] vol[50]"
  },
  {
    "time": "Sep 21 04:04:00.510",
    "process": "bt_player",
    "pid": "984",
    "message": "15:41:36, e[32mINFO e[0m e[90mprint_monitor:191:e[0m  BT    <X:X> [63894024240] power[1] discov[0] conn[0[] play[0] trans[BT_TRANSPORT_DISCONNECT:BT_TRANSPORT_IDLE] vol[64])"
  },
  {
    "time": "Sep 21 04:01:28.575",
    "process": "bt_player",
    "pid": "433",
    "message": "18:37:30, e[32mINFO e[0m e[90mprint_monitor:191:e[0m  BT    <X:X> [63894024088] power[1] discov[0] conn[0[] play[0] trans[BT_TRANSPORT_DISCONNECT:BT_TRANSPORT_IDLE] vol[64])"
  },
  {
    "time": "Sep 21 04:00:59.542",
    "process": "bt_player",
    "pid": "476",
    "message": "02:37:51, e[32mINFO e[0m e[90mprint_monitor:191:e[0m  BT    <X:X> [63894024059] power[1] discov[0] conn[0[] play[0] trans[BT_TRANSPORT_DISCONNECT:BT_TRANSPORT_IDLE] vol[64])"
  },
  {
    "time": "Sep 21 03:59:13.977",
    "process": "bt_player",
    "pid": "764",
    "message": "05:16:38, e[32mINFO e[0m e[90mprint_monitor:223:e[0m  TTS   <X:X> [63894023953] play[KIT_IDLE] vol[60]"
  },
  {
    "time": "Sep 21 03:53:34.516",
    "process": "bt_player",
    "pid": "865",
    "message": "00:37:31, e[32mINFO e[0m e[90mprint_monitor:223:e[0m  TTS   <X:X> [63894023614] play[KIT_IDLE] vol[60]"
  },
  {
    "time": "Sep 21 03:50:32.910",
    "process": "bt_player",
    "pid": "309",
    "message": "09:21:34, e[32mINFO e[0m e[90mprint_monitor:205:e[0m  MEDIA <X:X> [63894023432] play[KIT_STOPPED:000/000000] LED[0] HS[0] hplay[2] H_ID(000:-01) MT[1] vol[50]"
  },
  {
    "time": "Sep 21 03:48:56.993",
    "process": "bt_player",
    "pid": "142",
    "message": "11:31:38, e[32mINFO e[0m e[90mprint_monitor:205:e[0m  MEDIA <X:X> [63894023336] play[KIT_STOPPED:000/000000] LED[0] HS[0] hplay[2] H_ID(000:-01) MT[1] vol[50]"
  },
  {
    "time": "Sep 21 03:44:41.555",
    "process": "bt_player",
    "pid": "747",
    "message": "14:11:07, e[32mINFO e[0m e[90mprint_monitor:205:e[0m  MEDIA <X:X> [63894023081] play[KIT_STOPPED:000/000000] LED[0] HS[0] hplay[2] H_ID(000:-01) MT[1] vol[50]"
  },
  {
    "time": "Sep 21 03:44:14.724",
    "process": "bt_player",
    "pid": "537",
    "message": "10:36:59, e[32mINFO e[0m e[90mprint_monitor:191:e[0m  BT    <X:X> [63894023054] power[1] discov[0] conn[0[] play[0] trans[BT_TRANSPORT_DISCONNECT:BT_TRANSPORT_IDLE] vol[64])"
  },
  {
    "time": "Sep 21 03:36:26.192",
    "process": "bt_player",
    "pid": "726",
    "message": "04:53:57, e[32mINFO e[0m e[90mprint_monitor:223:e[0m  TTS   <X:X> [63894022586] play[KIT_IDLE] vol[60]"
  },
  {
    "time": "Sep 21 03:29:15.064",
    "process": "bt_player",
    "pid": "430",
    "message": "07:31:03, e[32mINFO e[0m e[90mprint_monitor:205:e[0m  MEDIA <X:X> [63894022155] play[KIT_STOPPED:000/000000] LED[0] HS[0] hplay[2] H_ID(000:-01) MT[1] vol[50]"
  },
  {
    "time": "Sep 21 03:27:03.695",
    "process": "bt_player",
    "pid": "500",
    "message": "12:38:57, e[32mINFO e[0m e[90mprint_monitor:191:e[0m  BT    <X:X> [63894022023] power[1] discov[0] conn[0[] play[0] trans[BT_TRANSPORT_DISCONNECT:BT_TRANSPORT_IDLE] vol[64])"
  },
  {
    "time": "Sep 21 03:24:34.436",
    "process": "bt_player",
    "pid": "650",
    "message": "09:45:44, e[32mINFO e[0m e[90mprint_monitor:191:e[0m  BT    <X:X> [63894021874] power[1] discov[0] conn[0[] play[0] trans[BT_TRANSPORT_DISCONNECT:BT_TRANSPORT_IDLE] vol[64])"
  },
  {
    "time": "Sep 21 03:20:07.150",
    "process": "bt_player",
    "pid": "772",
    "message": "08:11:52, e[32mINFO e[0m e[90mprint_monitor:223:e[0m  TTS   <X:X> [63894021607] play[KIT_IDLE] vol[60]"
  },
  {
    "time": "Sep 21 03:18:24.929",
    "process": "bt_player",
    "pid": "381",
    "message": "00:49:14, e[32mINFO e[0m e[90mprint_monitor:191:e[0m  BT    <X:X> [63894021504] power[1] discov[0] conn[0[] play[0] trans[BT_TRANSPORT_DISCONNECT:BT_TRANSPORT_IDLE] vol[64])"
  },
  {
    "time": "Sep 21 03:18:00.794",
    "process": "bt_player",
    "pid": "440",
    "message": "00:17:19, e[32mINFO e[0m e[90mprint_monitor:223:e[0m  TTS   <X:X> [63894021480] play[KIT_IDLE] vol[60]"
  },
  {
    "time": "Sep 21 03:12:01.117",
    "process": "bt_player",
    "pid": "666",
    "message": "19:51:47, e[32mINFO e[0m e[90mprint_monitor:191:e[0m  BT    <X:X> [63894021121] power[1] discov[0] conn[0[] play[0] trans[BT_TRANSPORT_DISCONNECT:BT_TRANSPORT_IDLE] vol[64])"
  },
  {
    "time": "Sep 21 03:09:28.614",
    "process": "bt_player",
    "pid": "470",
    "message": "08:12:41, e[32mINFO e[0m e[90mprint_monitor:205:e[0m  MEDIA <X:X> [63894020968] play[KIT_STOPPED:000/000000] LED[0] HS[0] hplay[2] H_ID(000:-01) MT[1] vol[50]"
  },
  {
    "time": "Sep 21 03:09:28.506",
    "process": "bt_player",
    "pid": "864",
    "message": "09:58:50, e[32mINFO e[0m e[90mprint_monitor:205:e[0m  MEDIA <X:X> [63894020968] play[KIT_STOPPED:000/000000] LED[0] HS[0] hplay[2] H_ID(000:-01) MT[1] vol[50]"
  },
  {
    "time": "Sep 21 03:07:57.634",
    "process": "bt_player",
    "pid": "845",
    "message": "05:50:06, e[32mINFO e[0m e[90mprint_monitor:191:e[0m  BT    <X:X> [63894020877] power[1] discov[0] conn[0[] play[0] trans[BT_TRANSPORT_DISCONNECT:BT_TRANSPORT_IDLE] vol[64])"
  },
  {
    "time": "Sep 21 03:07:10.989",
    "process": "bt_player",
    "pid": "422",
    "message": "20:28:37, e[32mINFO e[0m e[90mprint_monitor:191:e[0m  BT    <X:X> [63894020830] power[1] discov[0] conn[0[] play[0] trans[BT_TRANSPORT_DISCONNECT:BT_TRANSPORT_IDLE] vol[64])"
  },
  {
    "time": "Sep 21 03:06:04.905",
    "process": "bt_player",
    "pid": "214",
    "message": "19:49:44, e[32mINFO e[0m e[90mprint_monitor:191:e[0m  BT    <X:X> [63894020764] power[1] discov[0] conn[0[] play[0] trans[BT_TRANSPORT_DISCONNECT:BT_TRANSPORT_IDLE] vol[64])"
  },
  {
    "time": "Sep 21 03:04:33.808",
    "process": "bt_player",
    "pid": "318",
    "message": "23:44:30, e[32mINFO e[0m e[90mprint_monitor:205:e[0m  MEDIA <X:X> [63894020673] play[KIT_STOPPED:000/000000] LED[0] HS[0] hplay[2] H_ID(000:-01) MT[1] vol[50]"
  },
  {
    "time": "Sep 21 03:01:59.694",
    "process": "bt_player",
    "pid": "426",
    "message": "20:32:09, e[32mINFO e[0m e[90mprint_monitor:205:e[0m  MEDIA <X:X> [63894020519] play[KIT_STOPPED:000/000000] LED[0] HS[0] hplay[2] H_ID(000:-01) MT[1] vol[50]"
  },
  {
    "time": "Sep 21 03:01:26.821",
    "process": "bt_player",
    "pid": "660",
    "message": "14:04:23, e[32mINFO e[0m e[90mprint_monitor:205:e[0m  MEDIA <X:X> [63894020486] play[KIT_STOPPED:000/000000] LED[0] HS[0] hplay[2] H_ID(000:-01) MT[1] vol[50]"
  },
  {
    "time": "Sep 21 03:01:09.221",
    "process": "bt_player",
    "pid": "498",
    "message": "15:01:00, e[32mINFO e[0m e[90mprint_monitor:205:e[0m  MEDIA <X:X> [63894020469] play[KIT_STOPPED:000/000000] LED[0] HS[0] hplay[2] H_ID(000:-01) MT[1] vol[50]"
  },
  {
    "time": "Sep 21 03:00:46.047",
    "process": "bt_player",
    "pid": "908",
    "message": "11:46:50, e[32mINFO e[0m e[90mprint_monitor:223:e[0m  TTS   <X:X> [63894020446] play[KIT_IDLE] vol[60]"
  },
  {
    "time": "Sep 21 02:57:17.843",
    "process": "bt_player",
    "pid": "664",
    "message": "08:51:29, e[32mINFO e[0m e[90mprint_monitor:223:e[0m  TTS   <X:X> [63894020237] play[KIT_IDLE] vol[60]"
  },
  {
    "time": "Sep 21 02:56:37.109",
    "process": "bt_player",
    "pid": "855",
    "message": "22:57:58, e[32mINFO e[0m e[90mprint_monitor:191:e[0m  BT    <X:X> [63894020197] power[1] discov[0] conn[0[] play[0] trans[BT_TRANSPORT_DISCONNECT:BT_TRANSPORT_IDLE] vol[64])"
  },
  {
    "time": "Sep 21 02:56:35.074",
    "process": "bt_player",
    "pid": "266",
    "message": "21:13:12, e[32mINFO e[0m e[90mprint_monitor:223:e[0m  TTS   <X:X> [63894020195] play[KIT_IDLE] vol[60]"
  },
  {
    "time": "Sep 21 02:55:05.922",
    "process": "bt_player",
    "pid": "588",
    "message": "01:24:21, e[32mINFO e[0m e[90mprint_monitor:191:e[0m  BT    <X:X> [63894020105] power[1] discov[0] conn[0[] play[0] trans[BT_TRANSPORT_DISCONNECT:BT_TRANSPORT_IDLE] vol[64])"
  },
  {
    "time": "Sep 21 02:55:03.187",
    "process": "bt_player",
    "pid": "612",
    "message": "12:43:04, e[32mINFO e[0m e[90mprint_monitor:191:e[0m  BT    <X:X> [63894020103] power[1] discov[0] conn[0[] play[0] trans[BT_TRANSPORT_DISCONNECT:BT_TRANSPORT_IDLE] vol[64])"
  },
  {
    "time": "Sep 21 02:52:15.928",
    "process": "bt_player",
    "pid": "348",
    "message": "19:42:55, e[32mINFO e[0m e[90mprint_monitor:223:e[0m  TTS   <X:X> [63894019935] play[KIT_IDLE] vol[60]"
  },
  {
    "time": "Sep 21 02:49:56.611",
    "process": "bt_player",
    "pid": "280",
    "message": "00:22:46, e[32mINFO e[0m e[90mprint_monitor:205:e[0m  MEDIA <X:X> [63894019796] play[KIT_STOPPED:000/000000] LED[0] HS[0] hplay[2] H_ID(000:-01) MT[1] vol[50]"
  },
  {
    "time": "Sep 21 02:47:59.807",
    "process": "bt_player",
    "pid": "296",
    "message": "07:19:04, e[32mINFO e[0m e[90mprint_monitor:223:e[0m  TTS   <X:X> [63894019679] play[KIT_IDLE] vol[60]"
  },
  {
    "time": "Sep 21 02:47:51.905",
    "process": "bt_player",
    "pid": "241",
    "message": "01:50:03, e[32mINFO e[0m e[90mprint_monitor:223:e[0m  TTS   <X:X> [63894019671] play[KIT_IDLE] vol[60]"
  },
  {
    "time": "Sep 21 02:46:35.629",
    "process": "bt_player",
    "pid": "168",
    "message": "02:44:25, e[32mINFO e[0m e[90mprint_monitor:191:e[0m  BT    <X:X> [63894019595] power[1] discov[0] conn[0[] play[0] trans[BT_TRANSPORT_DISCONNECT:BT_TRANSPORT_IDLE] vol[64])"
  },
  {
    "time": "Sep 21 02:40:06.789",
    "process": "bt_player",
    "pid": "145",
    "message": "03:49:02, e[32mINFO e[0m e[90mprint_monitor:191:e[0m  BT    <X:X> [63894019206] power[1] discov[0] conn[0[] play[0] trans[BT_TRANSPORT_DISCONNECT:BT_TRANSPORT_IDLE] vol[64])"
  },
  {
    "time": "Sep 21 02:35:12.370",
    "process": "bt_player",
    "pid": "328",
    "message": "16:06:51, e[32mINFO e[0m e[90mprint_monitor:205:e[0m  MEDIA <X:X> [63894018912] play[KIT_STOPPED:000/000000] LED[0] HS[0] hplay[2] H_ID(000:-01) MT[1] vol[50]"
  },
  {
    "time": "Sep 21 02:29:22.317",
    "process": "bt_player",
    "pid": "800",
    "message": "18:57:33, e[32mINFO e[0m e[90mprint_monitor:191:e[0m  BT    <X:X> [63894018562] power[1] discov[0] conn[0[] play[0] trans[BT_TRANSPORT_DISCONNECT:BT_TRANSPORT_IDLE] vol[64])"
  },
  {
    "time": "Sep 21 02:24:32.107",
    "process": "bt_player",
    "pid": "519",
    "message": "01:07:37, e[32mINFO e[0m e[90mprint_monitor:223:e[0m  TTS   <X:X> [63894018272] play[KIT_IDLE] vol[60]"
  },
  {
    "time": "Sep 21 02:24:05.704",
    "process": "bt_player",
    "pid": "753",
    "message": "04:17:29, e[32mINFO e[0m e[90mprint_monitor:191:e[0m  BT    <X:X> [63894018245] power[1] discov[0] conn[0[] play[0] trans[BT_TRANSPORT_DISCONNECT:BT_TRANSPORT_IDLE] vol[64])"
  },
  {
    "time": "Sep 21 02:23:52.983",
    "process": "bt_player",
    "pid": "254",
    "message": "18:41:33, e[32mINFO e[0m e[90mprint_monitor:205:e[0m  MEDIA <X:X> [63894018232] play[KIT_STOPPED:000/000000] LED[0] HS[0] hplay[2] H_ID(000:-01) MT[1] vol[50]"
  },
  {
    "time": "Sep 21 02:23:12.728",
    "process": "bt_player",
    "pid": "661",
    "message": "20:56:51, e[32mINFO e[0m e[90mprint_monitor:191:e[0m  BT    <X:X> [63894018192] power[1] discov[0] conn[0[] play[0] trans[BT_TRANSPORT_DISCONNECT:BT_TRANSPORT_IDLE] vol[64])"
  },
  {
    "time": "Sep 21 02:18:07.543",
    "process": "bt_player",
    "pid": "696",
    "message": "07:43:12, e[32mINFO e[0m e[90mprint_monitor:205:e[0m  MEDIA <X:X> [63894017887] play[KIT_STOPPED:000/000000] LED[0] HS[0] hplay[2] H_ID(000:-01) MT[1] vol[50]"
  },
  {
    "time": "Sep 21 02:18:03.430",
    "process": "bt_player",
    "pid": "989",
    "message": "22:12:12, e[32mINFO e[0m e[90mprint_monitor:205:e[0m  MEDIA <X:X> [63894017883] play[KIT_STOPPED:000/000000] LED[0] HS[0] hplay[2] H_ID(000:-01) MT[1] vol[50]"
  },
  {
    "time": "Sep 21 02:17:16.514",
    "process": "bt_player",
    "pid": "759",
    "message": "16:35:05, e[32mINFO e[0m e[90mprint_monitor:191:e[0m  BT    <X:X> [63894017836] power[1] discov[0] conn[0[] play[0] trans[BT_TRANSPORT_DISCONNECT:BT_TRANSPORT_IDLE] vol[64])"
  },
  {
    "time": "Sep 21 02:17:09.863",
    "process": "bt_player",
    "pid": "605",
    "message": "05:26:02, e[32mINFO e[0m e[90mprint_monitor:191:e[0m  BT    <X:X> [63894017829] power[1] discov[0] conn[0[] play[0] trans[BT_TRANSPORT_DISCONNECT:BT_TRANSPORT_IDLE] vol[64])"
  },
  {
    "time": "Sep 21 02:16:58.079",
    "process": "bt_player",
    "pid": "269",
    "message": "22:35:31, e[32mINFO e[0m e[90mprint_monitor:223:e[0m  TTS   <X:X> [63894017818] play[KIT_IDLE] vol[60]"
  },
  {
    "time": "Sep 21 02:14:30.336",
    "process": "bt_player",
    "pid": "433",
    "message": "23:19:19, e[32mINFO e[0m e[90mprint_monitor:191:e[0m  BT    <X:X> [63894017670] power[1] discov[0] conn[0[] play[0] trans[BT_TRANSPORT_DISCONNECT:BT_TRANSPORT_IDLE] vol[64])"
  },
  {
    "time": "Sep 21 02:13:47.633",
    "process": "bt_player",
    "pid": "198",
    "message": "09:51:59, e[32mINFO e[0m e[90mprint_monitor:191:e[0m  BT    <X:X> [63894017627] power[1] discov[0] conn[0[] play[0] trans[BT_TRANSPORT_DISCONNECT:BT_TRANSPORT_IDLE] vol[64])"
  },
  {
    "time": "Sep 21 02:13:25.781",
    "process": "bt_player",
    "pid": "616",
    "message": "18:51:30, e[32mINFO e[0m e[90mprint_monitor:191:e[0m  BT    <X:X> [63894017605] power[1] discov[0] conn[0[] play[0] trans[BT_TRANSPORT_DISCONNECT:BT_TRANSPORT_IDLE] vol[64])"
  },
  {
    "time": "Sep 21 02:13:01.927",
    "process": "bt_player",
    "pid": "312",
    "message": "16:20:44, e[32mINFO e[0m e[90mprint_monitor:205:e[0m  MEDIA <X:X> [63894017581] play[KIT_STOPPED:000/000000] LED[0] HS[0] hplay[2] H_ID(000:-01) MT[1] vol[50]"
  },
  {
    "time": "Sep 21 02:13:00.123",
    "process": "bt_player",
    "pid": "593",
    "message": "03:15:15, e[32mINFO e[0m e[90mprint_monitor:191:e[0m  BT    <X:X> [63894017580] power[1] discov[0] conn[0[] play[0] trans[BT_TRANSPORT_DISCONNECT:BT_TRANSPORT_IDLE] vol[64])"
  },
  {
    "time": "Sep 21 02:12:13.098",
    "process": "bt_player",
    "pid": "898",
    "message": "23:39:24, e[32mINFO e[0m e[90mprint_monitor:205:e[0m  MEDIA <X:X> [63894017533] play[KIT_STOPPED:000/000000] LED[0] HS[0] hplay[2] H_ID(000:-01) MT[1] vol[50]"
  },
  {
    "time": "Sep 21 02:11:39.655",
    "process": "bt_player",
    "pid": "860",
    "message": "14:32:56, e[32mINFO e[0m e[90mprint_monitor:223:e[0m  TTS   <X:X> [63894017499] play[KIT_IDLE] vol[60]"
  },
  {
    "time": "Sep 21 02:09:52.645",
    "process": "bt_player",
    "pid": "979",
    "message": "06:41:06, e[32mINFO e[0m e[90mprint_monitor:191:e[0m  BT    <X:X> [63894017392] power[1] discov[0] conn[0[] play[0] trans[BT_TRANSPORT_DISCONNECT:BT_TRANSPORT_IDLE] vol[64])"
  },
  {
    "time": "Sep 21 02:09:13.649",
    "process": "bt_player",
    "pid": "880",
    "message": "11:28:53, e[32mINFO e[0m e[90mprint_monitor:191:e[0m  BT    <X:X> [63894017353] power[1] discov[0] conn[0[] play[0] trans[BT_TRANSPORT_DISCONNECT:BT_TRANSPORT_IDLE] vol[64])"
  },
  {
    "time": "Sep 21 02:06:43.658",
    "process": "bt_player",
    "pid": "525",
    "message": "00:36:43, e[32mINFO e[0m e[90mprint_monitor:223:e[0m  TTS   <X:X> [63894017203] play[KIT_IDLE] vol[60]"
  },
  {
    "time": "Sep 21 02:05:18.189",
    "process": "bt_player",
    "pid": "918",
    "message": "19:27:46, e[32mINFO e[0m e[90mprint_monitor:191:e[0m  BT    <X:X> [63894017118] power[1] discov[0] conn[0[] play[0] trans[BT_TRANSPORT_DISCONNECT:BT_TRANSPORT_IDLE] vol[64])"
  },
  {
    "time": "Sep 21 02:05:06.344",
    "process": "bt_player",
    "pid": "487",
    "message": "01:58:49, e[32mINFO e[0m e[90mprint_monitor:205:e[0m  MEDIA <X:X> [63894017106] play[KIT_STOPPED:000/000000] LED[0] HS[0] hplay[2] H_ID(000:-01) MT[1] vol[50]"
  },
  {
    "time": "Sep 21 02:00:14.688",
    "process": "bt_player",
    "pid": "259",
    "message": "10:00:44, e[32mINFO e[0m e[90mprint_monitor:205:e[0m  MEDIA <X:X> [63894016814] play[KIT_STOPPED:000/000000] LED[0] HS[0] hplay[2] H_ID(000:-01) MT[1] vol[50]"
  },
  {
    "time": "Sep 21 01:59:12.917",
    "process": "bt_player",
    "pid": "623",
    "message": "13:58:17, e[32mINFO e[0m e[90mprint_monitor:223:e[0m  TTS   <X:X> [63894016752] play[KIT_IDLE] vol[60]"
  },
  {
    "time": "Sep 21 01:56:10.344",
    "process": "bt_player",
    "pid": "203",
    "message": "01:07:01, e[32mINFO e[0m e[90mprint_monitor:223:e[0m  TTS   <X:X> [63894016570] play[KIT_IDLE] vol[60]"
  },
  {
    "time": "Sep 21 01:55:48.044",
    "process": "bt_player",
    "pid": "538",
    "message": "10:49:29, e[32mINFO e[0m e[90mprint_monitor:205:e[0m  MEDIA <X:X> [63894016548] play[KIT_STOPPED:000/000000] LED[0] HS[0] hplay[2] H_ID(000:-01) MT[1] vol[50]"
  },
  {
    "time": "Sep 21 01:54:48.083",
    "process": "bt_player",
    "pid": "356",
    "message": "07:28:53, e[32mINFO e[0m e[90mprint_monitor:205:e[0m  MEDIA <X:X> [63894016488] play[KIT_STOPPED:000/000000] LED[0] HS[0] hplay[2] H_ID(000:-01) MT[1] vol[50]"
  },
  {
    "time": "Sep 21 01:53:35.650",
    "process": "bt_player",
    "pid": "650",
    "message": "15:08:26, e[32mINFO e[0m e[90mprint_monitor:191:e[0m  BT    <X:X> [63894016415] power[1] discov[0] conn[0[] play[0] trans[BT_TRANSPORT_DISCONNECT:BT_TRANSPORT_IDLE] vol[64])"
  },
  {
    "time": "Sep 21 01:52:05.081",
    "process": "bt_player",
    "pid": "379",
    "message": "17:09:41, e[32mINFO e[0m e[90mprint_monitor:205:e[0m  MEDIA <X:X> [63894016325] play[KIT_STOPPED:000/000000] LED[0] HS[0] hplay[2] H_ID(000:-01) MT[1] vol[50]"
  },
  {
    "time": "Sep 21 01:49:20.842",
    "process": "bt_player",
    "pid": "757",
    "message": "07:27:19, e[32mINFO e[0m e[90mprint_monitor:191:e[0m  BT    <X:X> [63894016160] power[1] discov[0] conn[0[] play[0] trans[BT_TRANSPORT_DISCONNECT:BT_TRANSPORT_IDLE] vol[64])"
  },
  {
    "time": "Sep 21 01:47:29.149",
    "process": "bt_player",
    "pid": "422",
    "message": "06:49:38, e[32mINFO e[0m e[90mprint_monitor:205:e[0m  MEDIA <X:X> [63894016049] play[KIT_STOPPED:000/000000] LED[0] HS[0] hplay[2] H_ID(000:-01) MT[1] vol[50]"
  },
  {
    "time": "Sep 21 01:45:35.735",
    "process": "bt_player",
    "pid": "225",
    "message": "10:47:30, e[32mINFO e[0m e[90mprint_monitor:223:e[0m  TTS   <X:X> [63894015935] play[KIT_IDLE] vol[60]"
  },
  {
    "time": "Sep 21 01:39:55.657",
    "process": "bt_player",
    "pid": "359",
    "message": "06:37:38, e[32mINFO e[0m e[90mprint_monitor:223:e[0m  TTS   <X:X> [63894015595] play[KIT_IDLE] vol[60]"
  },
  {
    "time": "Sep 21 01:37:38.791",
    "process": "bt_player",
    "pid": "916",
    "message": "16:48:11, e[32mINFO e[0m e[90mprint_monitor:191:e[0m  BT    <X:X> [63894015458] power[1] discov[0] conn[0[] play[0] trans[BT_TRANSPORT_DISCONNECT:BT_TRANSPORT_IDLE] vol[64])"
  },
  {
    "time": "Sep 21 01:37:27.624",
    "process": "bt_player",
    "pid": "519",
    "message": "13:26:50, e[32mINFO e[0m e[90mprint_monitor:191:e[0m  BT    <X:X> [63894015447] power[1] discov[0] conn[0[] play[0] trans[BT_TRANSPORT_DISCONNECT:BT_TRANSPORT_IDLE] vol[64])"
  },
  {
    "time": "Sep 21 01:36:07.064",
    "process": "bt_player",
    "pid": "689",
    "message": "06:06:41, e[32mINFO e[0m e[90mprint_monitor:223:e[0m  TTS   <X:X> [63894015367] play[KIT_IDLE] vol[60]"
  },
  {
    "time": "Sep 21 01:35:44.516",
    "process": "bt_player",
    "pid": "317",
    "message": "04:49:43, e[32mINFO e[0m e[90mprint_monitor:205:e[0m  MEDIA <X:X> [63894015344] play[KIT_STOPPED:000/000000] LED[0] HS[0] hplay[2] H_ID(000:-01) MT[1] vol[50]"
  },
  {
    "time": "Sep 21 01:30:14.441",
    "process": "bt_player",
    "pid": "339",
    "message": "08:55:03, e[32mINFO e[0m e[90mprint_monitor:205:e[0m  MEDIA <X:X> [63894015014] play[KIT_STOPPED:000/000000] LED[0] HS[0] hplay[2] H_ID(000:-01) MT[1] vol[50]"
  },
  {
    "time": "Sep 21 01:27:00.042",
    "process": "bt_player",
    "pid": "299",
    "message": "06:09:49, e[32mINFO e[0m e[90mprint_monitor:191:e[0m  BT    <X:X> [63894014820] power[1] discov[0] conn[0[] play[0] trans[BT_TRANSPORT_DISCONNECT:BT_TRANSPORT_IDLE] vol[64])"
  },
  {
    "time": "Sep 21 01:25:32.008",
    "process": "bt_player",
    "pid": "192",
    "message": "03:07:35, e[32mINFO e[0m e[90mprint_monitor:191:e[0m  BT    <X:X> [63894014732] power[1] discov[0] conn[0[] play[0] trans[BT_TRANSPORT_DISCONNECT:BT_TRANSPORT_IDLE] vol[64])"
  },
  {
    "time": "Sep 21 01:24:29.124",
    "process": "bt_player",
    "pid": "158",
    "message": "17:16:06, e[32mINFO e[0m e[90mprint_monitor:191:e[0m  BT    <X:X> [63894014669] power[1] discov[0] conn[0[] play[0] trans[BT_TRANSPORT_DISCONNECT:BT_TRANSPORT_IDLE] vol[64])"
  },
  {
    "time": "Sep 21 01:23:05.400",
    "process": "bt_player",
    "pid": "774",
    "message": "01:29:46, e[32mINFO e[0m e[90mprint_monitor:205:e[0m  MEDIA <X:X> [63894014585] play[KIT_STOPPED:000/000000] LED[0] HS[0] hplay[2] H_ID(000:-01) MT[1] vol[50]"
  },
  {
    "time": "Sep 21 01:19:41.754",
    "process": "bt_player",
    "pid": "511",
    "message": "21:48:47, e[32mINFO e[0m e[90mprint_monitor:191:e[0m  BT    <X:X> [63894014381] power[1] discov[0] conn[0[] play[0] trans[BT_TRANSPORT_DISCONNECT:BT_TRANSPORT_IDLE] vol[64])"
  },
  {
    "time": "Sep 21 01:18:47.665",
    "process": "bt_player",
    "pid": "219",
    "message": "20:10:56, e[32mINFO e[0m e[90mprint_monitor:223:e[0m  TTS   <X:X> [63894014327] play[KIT_IDLE] vol[60]"
  },
  {
    "time": "Sep 21 01:17:19.672",
    "process": "bt_player",
    "pid": "588",
    "message": "14:42:26, e[32mINFO e[0m e[90mprint_monitor:191:e[0m  BT    <X:X> [63894014239] power[1] discov[0] conn[0[] play[0] trans[BT_TRANSPORT_DISCONNECT:BT_TRANSPORT_IDLE] vol[64])"
  },
  {
    "time": "Sep 21 01:16:32.540",
    "process": "bt_player",
    "pid": "722",
    "message": "05:56:00, e[32mINFO e[0m e[90mprint_monitor:191:e[0m  BT    <X:X> [63894014192] power[1] discov[0] conn[0[] play[0] trans[BT_TRANSPORT_DISCONNECT:BT_TRANSPORT_IDLE] vol[64])"
  },
  {
    "time": "Sep 21 01:15:11.144",
    "process": "bt_player",
    "pid": "578",
    "message": "23:58:07, e[32mINFO e[0m e[90mprint_monitor:223:e[0m  TTS   <X:X> [63894014111] play[KIT_IDLE] vol[60]"
  },
  {
    "time": "Sep 21 01:11:04.768",
    "process": "bt_player",
    "pid": "213",
    "message": "17:30:41, e[32mINFO e[0m e[90mprint_monitor:205:e[0m  MEDIA <X:X> [63894013864] play[KIT_STOPPED:000/000000] LED[0] HS[0] hplay[2] H_ID(000:-01) MT[1] vol[50]"
  },
  {
    "time": "Sep 21 01:08:40.978",
    "process": "bt_player",
    "pid": "739",
    "message": "09:00:54, e[32mINFO e[0m e[90mprint_monitor:205:e[0m  MEDIA <X:X> [63894013720] play[KIT_STOPPED:000/000000] LED[0] HS[0] hplay[2] H_ID(000:-01) MT[1] vol[50]"
  },
  {
    "time": "Sep 21 01:06:53.356",
    "process": "bt_player",
    "pid": "164",
    "message": "15:22:12, e[32mINFO e[0m e[90mprint_monitor:223:e[0m  TTS   <X:X> [63894013613] play[KIT_IDLE] vol[60]"
  },
  {
    "time": "Sep 21 01:05:27.072",
    "process": "bt_player",
    "pid": "890",
    "message": "00:06:37, e[32mINFO e[0m e[90mprint_monitor:191:e[0m  BT    <X:X> [63894013527] power[1] discov[0] conn[0[] play[0] trans[BT_TRANSPORT_DISCONNECT:BT_TRANSPORT_IDLE] vol[64])"
  },
  {
    "time": "Sep 21 01:04:35.122",
    "process": "bt_player",
    "pid": "474",
    "message": "17:20:42, e[32mINFO e[0m e[90mprint_monitor:223:e[0m  TTS   <X:X> [63894013475] play[KIT_IDLE] vol[60]"
  },
  {
    "time": "Sep 21 01:03:03.930",
    "process": "bt_player",
    "pid": "650",
    "message": "21:58:04, e[32mINFO e[0m e[90mprint_monitor:191:e[0m  BT    <X:X> [63894013383] power[1] discov[0] conn[0[] play[0] trans[BT_TRANSPORT_DISCONNECT:BT_TRANSPORT_IDLE] vol[64])"
  },
  {
    "time": "Sep 21 00:59:27.598",
    "process": "bt_player",
    "pid": "858",
    "message": "13:13:03, e[32mINFO e[0m e[90mprint_monitor:223:e[0m  TTS   <X:X> [63894013167] play[KIT_IDLE] vol[60]"
  },
  {
    "time": "Sep 21 00:55:39.327",
    "process": "bt_player",
    "pid": "872",
    "message": "23:26:38, e[32mINFO e[0m e[90mprint_monitor:205:e[0m  MEDIA <X:X> [63894012939] play[KIT_STOPPED:000/000000] LED[0] HS[0] hplay[2] H_ID(000:-01) MT[1] vol[50]"
  },
  {
    "time": "Sep 21 00:52:16.237",
    "process": "bt_player",
    "pid": "636",
    "message": "16:47:33, e[32mINFO e[0m e[90mprint_monitor:191:e[0m  BT    <X:X> [63894012736] power[1] discov[0] conn[0[] play[0] trans[BT_TRANSPORT_DISCONNECT:BT_TRANSPORT_IDLE] vol[64])"
  },
  {
    "time": "Sep 21 00:51:45.556",
    "process": "bt_player",
    "pid": "642",
    "message": "01:39:50, e[32mINFO e[0m e[90mprint_monitor:223:e[0m  TTS   <X:X> [63894012705] play[KIT_IDLE] vol[60]"
  },
  {
    "time": "Sep 21 00:51:04.710",
    "process": "bt_player",
    "pid": "249",
    "message": "05:19:12, e[32mINFO e[0m e[90mprint_monitor:191:e[0m  BT    <X:X> [63894012664] power[1] discov[0] conn[0[] play[0] trans[BT_TRANSPORT_DISCONNECT:BT_TRANSPORT_IDLE] vol[64])"
  },
  {
    "time": "Sep 21 00:42:14.271",
    "process": "bt_player",
    "pid": "895",
    "message": "09:01:52, e[32mINFO e[0m e[90mprint_monitor:191:e[0m  BT    <X:X> [63894012134] power[1] discov[0] conn[0[] play[0] trans[BT_TRANSPORT_DISCONNECT:BT_TRANSPORT_IDLE] vol[64])"
  },
  {
    "time": "Sep 21 00:35:57.482",
    "process": "bt_player",
    "pid": "261",
    "message": "05:22:52, e[32mINFO e[0m e[90mprint_monitor:205:e[0m  MEDIA <X:X> [63894011757] play[KIT_STOPPED:000/000000] LED[0] HS[0] hplay[2] H_ID(000:-01) MT[1] vol[50]"
  },
  {
    "time": "Sep 21 00:31:45.371",
    "process": "bt_player",
    "pid": "738",
    "message": "03:51:42, e[32mINFO e[0m e[90mprint_monitor:205:e[0m  MEDIA <X:X> [63894011505] play[KIT_STOPPED:000/000000] LED[0] HS[0] hplay[2] H_ID(000:-01) MT[1] vol[50]"
  },
  {
    "time": "Sep 21 00:24:24.484",
    "process": "bt_player",
    "pid": "591",
    "message": "21:52:32, e[32mINFO e[0m e[90mprint_monitor:223:e[0m  TTS   <X:X> [63894011064] play[KIT_IDLE] vol[60]"
  },
  {
    "time": "Sep 21 00:20:42.478",
    "process": "bt_player",
    "pid": "546",
    "message": "14:15:15, e[32mINFO e[0m e[90mprint_monitor:191:e[0m  BT    <X:X> [63894010842] power[1] discov[0] conn[0[] play[0] trans[BT_TRANSPORT_DISCONNECT:BT_TRANSPORT_IDLE] vol[64])"
  },
  {
    "time": "Sep 21 00:17:37.958",
    "process": "bt_player",
    "pid": "491",
    "message": "09:30:56, e[32mINFO e[0m e[90mprint_monitor:191:e[0m  BT    <X:X> [63894010657] power[1] discov[0] conn[0[] play[0] trans[BT_TRANSPORT_DISCONNECT:BT_TRANSPORT_IDLE] vol[64])"
  },
  {
    "time": "Sep 21 00:16:21.346",
    "process": "bt_player",
    "pid": "802",
    "message": "04:37:28, e[32mINFO e[0m e[90mprint_monitor:205:e[0m  MEDIA <X:X> [63894010581] play[KIT_STOPPED:000/000000] LED[0] HS[0] hplay[2] H_ID(000:-01) MT[1] vol[50]"
  },
  {
    "time": "Sep 21 00:10:18.037",
    "process": "bt_player",
    "pid": "202",
    "message": "15:22:31, e[32mINFO e[0m e[90mprint_monitor:205:e[0m  MEDIA <X:X> [63894010218] play[KIT_STOPPED:000/000000] LED[0] HS[0] hplay[2] H_ID(000:-01) MT[1] vol[50]"
  },
  {
    "time": "Sep 21 00:06:12.457",
    "process": "bt_player",
    "pid": "808",
    "message": "14:46:42, e[32mINFO e[0m e[90mprint_monitor:191:e[0m  BT    <X:X> [63894009972] power[1] discov[0] conn[0[] play[0] trans[BT_TRANSPORT_DISCONNECT:BT_TRANSPORT_IDLE] vol[64])"
  },
  {
    "time": "Sep 21 00:06:09.569",
    "process": "bt_player",
    "pid": "775",
    "message": "14:02:56, e[32mINFO e[0m e[90mprint_monitor:191:e[0m  BT    <X:X> [63894009969] power[1] discov[0] conn[0[] play[0] trans[BT_TRANSPORT_DISCONNECT:BT_TRANSPORT_IDLE] vol[64])"
  },
  {
    "time": "Sep 21 00:06:05.826",
    "process": "bt_player",
    "pid": "653",
    "message": "22:31:48, e[32mINFO e[0m e[90mprint_monitor:223:e[0m  TTS   <X:X> [63894009965] play[KIT_IDLE] vol[60]"
  },
  {
    "time": "Sep 21 00:03:00.865",
    "process": "bt_player",
    "pid": "332",
    "message": "16:08:55, e[32mINFO e[0m e[90mprint_monitor:223:e[0m  TTS   <X:X> [63894009780] play[KIT_IDLE] vol[60]"
  },
  {
    "time": "Sep 21 00:01:05.247",
    "process": "bt_player",
    "pid": "884",
    "message": "04:40:51, e[32mINFO e[0m e[90mprint_monitor:191:e[0m  BT    <X:X> [63894009665] power[1] discov[0] conn[0[] play[0] trans[BT_TRANSPORT_DISCONNECT:BT_TRANSPORT_IDLE] vol[64])"
  },
  {
    "time": "Sep 21 00:00:41.987",
    "process": "bt_player",
    "pid": "897",
    "message": "21:37:12, e[32mINFO e[0m e[90mprint_monitor:223:e[0m  TTS   <X:X> [63894009641] play[KIT_IDLE] vol[60]"
  },
  {
    "time": "Sep 20 23:55:50.545",
    "process": "bt_player",
    "pid": "203",
    "message": "01:10:00, e[32mINFO e[0m e[90mprint_monitor:223:e[0m  TTS   <X:X> [63894009350] play[KIT_IDLE] vol[60]"
  },
  {
    "time": "Sep 20 23:51:42.650",
    "process": "bt_player",
    "pid": "478",
    "message": "13:39:18, e[32mINFO e[0m e[90mprint_monitor:205:e[0m  MEDIA <X:X> [63894009102] play[KIT_STOPPED:000/000000] LED[0] HS[0] hplay[2] H_ID(000:-01) MT[1] vol[50]"
  },
  {
    "time": "Sep 20 23:49:17.715",
    "process": "bt_player",
    "pid": "323",
    "message": "03:48:02, e[32mINFO e[0m e[90mprint_monitor:205:e[0m  MEDIA <X:X> [63894008957] play[KIT_STOPPED:000/000000] LED[0] HS[0] hplay[2] H_ID(000:-01) MT[1] vol[50]"
  },
  {
    "time": "Sep 20 23:44:22.581",
    "process": "bt_player",
    "pid": "830",
    "message": "06:22:31, e[32mINFO e[0m e[90mprint_monitor:191:e[0m  BT    <X:X> [63894008662] power[1] discov[0] conn[0[] play[0] trans[BT_TRANSPORT_DISCONNECT:BT_TRANSPORT_IDLE] vol[64])"
  },
  {
    "time": "Sep 20 23:37:48.143",
    "process": "bt_player",
    "pid": "164",
    "message": "20:37:57, e[32mINFO e[0m e[90mprint_monitor:191:e[0m  BT    <X:X> [63894008268] power[1] discov[0] conn[0[] play[0] trans[BT_TRANSPORT_DISCONNECT:BT_TRANSPORT_IDLE] vol[64])"
  },
  {
    "time": "Sep 20 23:36:31.180",
    "process": "bt_player",
    "pid": "906",
    "message": "03:46:20, e[32mINFO e[0m e[90mprint_monitor:223:e[0m  TTS   <X:X> [63894008191] play[KIT_IDLE] vol[60]"
  },
  {
    "time": "Sep 20 23:36:30.262",
    "process": "bt_player",
    "pid": "819",
    "message": "01:40:49, e[32mINFO e[0m e[90mprint_monitor:223:e[0m  TTS   <X:X> [63894008190] play[KIT_IDLE] vol[60]"
  },
  {
    "time": "Sep 20 23:35:13.743",
    "process": "bt_player",
    "pid": "131",
    "message": "06:28:22, e[32mINFO e[0m e[90mprint_monitor:205:e[0m  MEDIA <X:X> [63894008113] play[KIT_STOPPED:000/000000] LED[0] HS[0] hplay[2] H_ID(000:-01) MT[1] vol[50]"
  },
  {
    "time": "Sep 20 23:33:02.018",
    "process": "bt_player",
    "pid": "296",
    "message": "07:08:39, e[32mINFO e[0m e[90mprint_monitor:223:e[0m  TTS   <X:X> [63894007982] play[KIT_IDLE] vol[60]"
  },
  {
    "time": "Sep 20 23:32:29.213",
    "process": "bt_player",
    "pid": "362",
    "message": "11:03:33, e[32mINFO e[0m e[90mprint_monitor:191:e[0m  BT    <X:X> [63894007949] power[1] discov[0] conn[0[] play[0] trans[BT_TRANSPORT_DISCONNECT:BT_TRANSPORT_IDLE] vol[64])"
  },
  {
    "time": "Sep 20 23:30:00.569",
    "process": "bt_player",
    "pid": "550",
    "message": "17:35:16, e[32mINFO e[0m e[90mprint_monitor:205:e[0m  MEDIA <X:X> [63894007800] play[KIT_STOPPED:000/000000] LED[0] HS[0] hplay[2] H_ID(000:-01) MT[1] vol[50]"
  },
  {
    "time": "Sep 20 23:17:12.555",
    "process": "bt_player",
    "pid": "583",
    "message": "18:54:47, e[32mINFO e[0m e[90mprint_monitor:205:e[0m  MEDIA <X:X> [63894007032] play[KIT_STOPPED:000/000000] LED[0] HS[0] hplay[2] H_ID(000:-01) MT[1] vol[50]"
  },
  {
    "time": "Sep 20 23:15:24.752",
    "process": "bt_player",
    "pid": "741",
    "message": "02:27:03, e[32mINFO e[0m e[90mprint_monitor:191:e[0m  BT    <X:X> [63894006924] power[1] discov[0] conn[0[] play[0] trans[BT_TRANSPORT_DISCONNECT:BT_TRANSPORT_IDLE] vol[64])"
  },
  {
    "time": "Sep 20 23:13:52.231",
    "process": "bt_player",
    "pid": "580",
    "message": "05:14:59, e[32mINFO e[0m e[90mprint_monitor:223:e[0m  TTS   <X:X> [63894006832] play[KIT_IDLE] vol[60]"
  }
]